{
  "intents": [
    {
      "tag": "greeting",
      "patterns": [
        "Hi",
        "Hey",
        "How are you",
        "Hello"
      ],
      "responses": [
        "Hi there, Welcome to KCT how can I help?"
      ]
    },
    {
      "tag": "goodbye",
      "patterns": ["Bye", "See you later", "Goodbye"],
      "responses": [
        "See you later, thanks for visiting",
        "Have a nice day"
      ]
    },
    {
      "tag": "thanks",
      "patterns": ["Thanks", "Thank you", "That's helpful", "Thank's a lot!"],
      "responses": ["Happy to help!","My pleasure"]
    },
    {
      "tag": "admin",
      "patterns": [
        "where is admin block?",
        "girls hostel",
        "boys hostel",
        "B block",
        "C block",
        "D block",
        "E block",
        "kore"
      ],
      "responses": [
        "Please use the above navigation box enter the location you want to go!"
      ]
    },
    {
      "tag": "food",
      "patterns": [
        "snacks",
        "food",
        "lunch",
        "breakfast",
        "cafe coffee day",
        "ccd",
        "kore",
        "east kore",
        "where can i get lunch",
        "where can i get snack",
        "i am hungry",
        "juice",
        "where can i buy juice",
        "eat"
      ],
      "responses": [
        "You can search for kore, east kore, or k's cafe in the navigation box"
      ]
    },
    {
      "tag": "clubs",
      "patterns": [
        "available clubs",
        "clubs in kct",
        "clubs"
      ],
      "responses": [
        "Some available clubs at KCT are Varnam, evoke, band agartha, studio kct, iQube, SOIL, etc.\nFor more info visit: https://www.kct.ac.in/office-of-student-affairs/"
      ]
    }
  ]
}
